proximatic/__init__.py
proximatic/cli.py
proximatic/core.py
proximatic/main.py
proximatic/models.py
proximatic/restapi.py
proximatic/runhttp.py
proximatic/utils.py
proximatic-0.1.7.dist-info/entry_points.txt
proximatic-0.1.7.dist-info/LICENSE.md
proximatic-0.1.7.dist-info/WHEEL
proximatic-0.1.7.dist-info/METADATA
proximatic-0.1.7.dist-info/RECORD
